YouML/.DS_Store
YouML/Main.so
YouML/__init__.py
YouML/LG/.DS_Store
YouML/LG/MainWindow.so
YouML/LG/Basic/Alph.so
YouML/LG/Basic/CssTip.so
YouML/LG/Basic/CtrlSigConn.so
YouML/LG/Basic/DBInit.so
YouML/LG/Basic/NamConv.so
YouML/LG/Basic/NumConv.so
YouML/LG/Basic/PanLay.so
YouML/LG/Basic/PlcHodr.so
YouML/LG/Basic/RmZero.so
YouML/LG/Basic/SizScal.so
YouML/LG/Basic/ThrdStp.so
YouML/LG/Basic/TxtEld.so
YouML/LG/Basic/UniReg.so
YouML/LG/Data/DatImp.so
YouML/LG/Data/DatKg.so
YouML/LG/Data/DatLst.so
YouML/LG/Data/PanDatInit.so
YouML/LG/Data/RankAlgExec.so
YouML/LG/Data/RankAlgInit.so
YouML/LG/Data/TbFil.so
YouML/LG/Data/WgtDatItmCld.so
YouML/LG/Data/WgtDatItmLoc.so
YouML/LG/Data/WgtTbHdr.so
YouML/LG/Data/WgtTbHdrFig.so
YouML/LG/Experiment/PanExpInit.so
YouML/LG/Experiment/WgtExpItm.so
YouML/LG/General/Ani.so
YouML/LG/General/LstItmAdd.so
YouML/LG/General/MultiProc.so
YouML/LG/General/PanDatSav.so
YouML/LG/General/PanIcnSw.so
YouML/LG/General/PanSw.so
YouML/LG/General/SidHistAdj.so
YouML/LG/General/SidHistManiUpd.so
YouML/LG/General/WgtSidHist.so
YouML/LG/General/WgtSidHistItm.so
YouML/LG/General/WgtSidStrBtm.so
YouML/LG/General/WgtSidStrLeft.so
YouML/LG/General/WgtSidStrRt.so
YouML/LG/General/WgtSidTask.so
YouML/LG/General/WgtSidTaskBox.so
YouML/LG/General/WgtSidTaskItm.so
YouML/LG/General/WgtSidWarn.so
YouML/LG/General/WgtThrd.so
YouML/LG/Modeling/MdlAlgExec.so
YouML/LG/Modeling/MdlAlgInit.so
YouML/LG/Modeling/MdlExec.so
YouML/LG/Modeling/PanMdlInit.so
YouML/LG/Modeling/WgtMdlFig.so
YouML/LG/Modeling/WgtMdlFigInf.so
YouML/LG/Modeling/WgtMdlInf.so
YouML/LG/Processing/PanProcInit.so
YouML/LG/Processing/ProcAlgExec.so
YouML/LG/Processing/ProcAlgInit.so
YouML/LG/Processing/ProcExec.so
YouML/LG/Processing/TbProc.so
YouML/LG/Processing/WgtFrm.so
YouML/LG/Processing/WgtProcAlgItm.so
YouML/LG/Processing/WgtProcAlgParaDpd.so
YouML/LG/Processing/WgtProcAlgParaNum.so
YouML/LG/Processing/WgtProcAlgParaSw.so
YouML/LG/Processing/WgtProcAlgParaTxt.so
YouML/LG/Processing/WgtProcColCand.so
YouML-0.6.0.dist-info/METADATA
YouML-0.6.0.dist-info/WHEEL
YouML-0.6.0.dist-info/entry_points.txt
YouML-0.6.0.dist-info/top_level.txt
YouML-0.6.0.dist-info/RECORD
