Metadata-Version: 2.1
Name: YouML
Version: 0.6.0
Summary: A Machine Learning Toolkit
Home-page: https://github.com/ChongyaSong/YouML
Author: Chongya Song
Author-email: schongy523@gmail.com
License: UNKNOWN
Platform: MacOS
Platform: Linux
Platform: Windows Subsystem for Linux (WSL)
Requires-Python: ==3.7.11
Requires-Dist: xlrd
Requires-Dist: tqdm
Requires-Dist: apsw
Requires-Dist: blist
Requires-Dist: cycler
Requires-Dist: psutil
Requires-Dist: slugify
Requires-Dist: urllib3
Requires-Dist: requests
Requires-Dist: openpyxl
Requires-Dist: pycryptodome
Requires-Dist: scikit-learn-intelex (==2021.4.0)
Requires-Dist: scikit-learn (==0.24.2)
Requires-Dist: matplotlib (==3.4.2)
Requires-Dist: pandas (==1.3.2)
Requires-Dist: numpy (==1.20.3)
Requires-Dist: scipy (==1.7.1)
Requires-Dist: pyqt5 (==5.9.2)
